<?xml version="1.0" encoding="UTF-8"?>
<zabbix_export><version>6.0</version><date>2023-02-11T16:14:54Z</date><groups><group><uuid>3dcd5bbe90534f9e8eb5c2d53756af63</uuid><name>Templates/Power</name></group></groups><templates><template><uuid>4ffb0f9103084384a98379ed533865e9</uuid><template>APC UPS Symmetra RX by SNMP</template><name>APC UPS Symmetra RX by SNMP</name><description>Template Power APC UPS Symmetra RX

MIBs used:
HOST-RESOURCES-MIB
PowerNet-MIB
SNMPv2-MIB

You can discuss this template or leave feedback on our forum https://www.zabbix.com/forum/zabbix-suggestions-and-feedback/420730-discussion-thread-for-official-zabbix-template-apc-ups

Template tooling version used: 0.41</description><groups><group><name>Templates/Power</name></group></groups><items><item><uuid>0f45eeef24724e3b89760b04bfd037ae</uuid><name>Battery capacity</name><type>SNMP_AGENT</type><snmp_oid>1.3.6.1.4.1.318.1.1.1.2.3.1.0</snmp_oid><key>battery.capacity[upsHighPrecBatteryCapacity]</key><history>7d</history><value_type>FLOAT</value_type><units>%</units><description>MIB: PowerNet-MIB
The remaining battery capacity expressed as
 percentage of full capacity.</description><preprocessing><step><type>MULTIPLIER</type><parameters><parameter>0.1</parameter></parameters></step><step><type>DISCARD_UNCHANGED_HEARTBEAT</type><parameters><parameter>6h</parameter></parameters></step></preprocessing><tags><tag><tag>component</tag><value>power</value></tag></tags><triggers><trigger><uuid>5626e87891ec4c28a17a6b5965b47e46</uuid><expression>last(/APC UPS Symmetra RX by SNMP/battery.capacity[upsHighPrecBatteryCapacity]) &lt; {$BATTERY.CAPACITY.MIN.WARN}</expression><name>Battery has low capacity</name><event_name>Battery has low capacity (below {$BATTERY.CAPACITY.MIN.WARN}%)</event_name><opdata>Current capacity: {ITEM.LASTVALUE1}</opdata><priority>HIGH</priority><tags><tag><tag>scope</tag><value>capacity</value></tag></tags></trigger></triggers></item><item><uuid>a40074f9db134bc8bc4bd9800906137d</uuid><name>External battery packs count</name><type>SNMP_AGENT</type><snmp_oid>1.3.6.1.4.1.318.1.1.1.2.2.5.0</snmp_oid><key>battery.external_packs_count[upsAdvBatteryNumOfBattPacks]</key><delay>1h</delay><history>7d</history><description>MIB: PowerNet-MIB
The number of external battery packs connected to the UPS. If
 the UPS does not use smart cells then the agent reports
 ERROR_NO_SUCH_NAME.</description><preprocessing><step><type>DISCARD_UNCHANGED_HEARTBEAT</type><parameters><parameter>6h</parameter></parameters></step></preprocessing><tags><tag><tag>component</tag><value>inventory</value></tag></tags></item><item><uuid>c069bb03f58a47b981448a33a1663463</uuid><name>Battery last replace date</name><type>SNMP_AGENT</type><snmp_oid>1.3.6.1.4.1.318.1.1.1.2.1.3.0</snmp_oid><key>battery.last_replace_date[upsBasicBatteryLastReplaceDate]</key><delay>1h</delay><history>7d</history><trends>0</trends><value_type>CHAR</value_type><description>MIB: PowerNet-MIB
The date when the UPS system's batteries were last replaced
 in mm/dd/yy (or yyyy) format. For Smart-UPS models, this value
 is originally set at the factory. When the UPS batteries
 are replaced, this value should be reset by the administrator.
 For Symmetra PX 250/500 this OID is read-only and is configurable in the local display only.</description><preprocessing><step><type>DISCARD_UNCHANGED_HEARTBEAT</type><parameters><parameter>6h</parameter></parameters></step></preprocessing><tags><tag><tag>component</tag><value>inventory</value></tag></tags></item><item><uuid>810c9cd371c14e44b8670ad3f4e003d5</uuid><name>Battery replace indicator</name><type>SNMP_AGENT</type><snmp_oid>1.3.6.1.4.1.318.1.1.1.2.2.4.0</snmp_oid><key>battery.replace_indicator[upsAdvBatteryReplaceIndicator]</key><history>7d</history><description>MIB: PowerNet-MIB
Indicates whether the UPS batteries need replacement.</description><valuemap><name>PowerNet-MIB::upsAdvBatteryReplaceIndicator</name></valuemap><preprocessing><step><type>DISCARD_UNCHANGED_HEARTBEAT</type><parameters><parameter>6h</parameter></parameters></step></preprocessing><tags><tag><tag>component</tag><value>power</value></tag></tags><triggers><trigger><uuid>a74eccd4442c401a98ac3c80dd3baa13</uuid><expression>last(/APC UPS Symmetra RX by SNMP/battery.replace_indicator[upsAdvBatteryReplaceIndicator])=2</expression><name>Battery needs replacement</name><priority>HIGH</priority><description>A battery installed has an internal error condition.</description><tags><tag><tag>scope</tag><value>notice</value></tag></tags></trigger></triggers></item><item><uuid>849b9ffa0c0b4dd59e7c5a544a135fa3</uuid><name>Battery runtime remaining</name><type>SNMP_AGENT</type><snmp_oid>1.3.6.1.4.1.318.1.1.1.2.2.3.0</snmp_oid><key>battery.runtime_remaining[upsAdvBatteryRunTimeRemaining]</key><history>7d</history><value_type>FLOAT</value_type><units>s</units><description>MIB: PowerNet-MIB
The UPS battery run time remaining before battery
 exhaustion.</description><preprocessing><step><type>MULTIPLIER</type><parameters><parameter>0.01</parameter></parameters></step><step><type>DISCARD_UNCHANGED_HEARTBEAT</type><parameters><parameter>6h</parameter></parameters></step></preprocessing><tags><tag><tag>component</tag><value>power</value></tag></tags></item><item><uuid>a5ccdee4e5ff49f183adab8a283e88a0</uuid><name>Battery status</name><type>SNMP_AGENT</type><snmp_oid>1.3.6.1.4.1.318.1.1.1.2.1.1.0</snmp_oid><key>battery.status[upsBasicBatteryStatus]</key><history>7d</history><description>MIB: PowerNet-MIB
The status of the UPS batteries. A batteryLow(3) value
 indicates the UPS will be unable to sustain the current
 load, and its services will be lost if power is not restored.
 The amount of run time in reserve at the time of low battery
 can be configured by the upsAdvConfigLowBatteryRunTime.
 A batteryInFaultCondition(4)value indicates that a battery
 installed has an internal error condition.</description><valuemap><name>PowerNet-MIB::upsBasicBatteryStatus</name></valuemap><preprocessing><step><type>DISCARD_UNCHANGED_HEARTBEAT</type><parameters><parameter>6h</parameter></parameters></step></preprocessing><tags><tag><tag>component</tag><value>health</value></tag><tag><tag>component</tag><value>power</value></tag></tags><triggers><trigger><uuid>107454c372cb413bad4d4a807c254ae0</uuid><expression>last(/APC UPS Symmetra RX by SNMP/battery.status[upsBasicBatteryStatus])=4</expression><name>Battery has an internal error condition</name><priority>AVERAGE</priority><description>A battery installed has an internal error condition.</description><tags><tag><tag>scope</tag><value>notice</value></tag></tags></trigger><trigger><uuid>4a410279dba04d37924eade4bb927228</uuid><expression>last(/APC UPS Symmetra RX by SNMP/battery.status[upsBasicBatteryStatus])=3</expression><name>Battery is Low</name><priority>AVERAGE</priority><description>The UPS will be unable to sustain the current load, and its services will be lost if power is not restored.</description><tags><tag><tag>scope</tag><value>capacity</value></tag></tags></trigger></triggers></item><item><uuid>59cc2d65eca142adb00ec80e237b134e</uuid><name>Battery temperature</name><type>SNMP_AGENT</type><snmp_oid>1.3.6.1.4.1.318.1.1.1.2.3.2.0</snmp_oid><key>battery.temperature[upsHighPrecBatteryTemperature]</key><history>7d</history><value_type>FLOAT</value_type><units>℃</units><description>MIB: PowerNet-MIB
The current internal UPS temperature in Celsius.
 Temperatures below zero read as 0.</description><preprocessing><step><type>MULTIPLIER</type><parameters><parameter>0.1</parameter></parameters></step><step><type>DISCARD_UNCHANGED_HEARTBEAT</type><parameters><parameter>6h</parameter></parameters></step></preprocessing><tags><tag><tag>component</tag><value>temperature</value></tag></tags><triggers><trigger><uuid>225ccc34992f4c718277b436bfecdc72</uuid><expression>min(/APC UPS Symmetra RX by SNMP/battery.temperature[upsHighPrecBatteryTemperature],{$TIME.PERIOD}) &gt; {$BATTERY.TEMP.MAX.WARN}</expression><name>Battery has high temperature</name><event_name>Battery has high temperature (over {$BATTERY.TEMP.MAX.WARN}℃ for {$TIME.PERIOD})</event_name><opdata>Current temperature: {ITEM.LASTVALUE1}</opdata><priority>HIGH</priority><tags><tag><tag>scope</tag><value>notice</value></tag></tags></trigger></triggers></item><item><uuid>ae8516a825b94d90b267371934bc452f</uuid><name>Battery voltage</name><type>SNMP_AGENT</type><snmp_oid>1.3.6.1.4.1.318.1.1.1.2.3.4.0</snmp_oid><key>battery.voltage[upsHighPrecBatteryActualVoltage]</key><history>7d</history><value_type>FLOAT</value_type><units>V</units><description>MIB: PowerNet-MIB
The actual battery bus voltage in Volts.</description><preprocessing><step><type>MULTIPLIER</type><parameters><parameter>0.1</parameter></parameters></step><step><type>DISCARD_UNCHANGED_HEARTBEAT</type><parameters><parameter>6h</parameter></parameters></step></preprocessing><tags><tag><tag>component</tag><value>power</value></tag></tags></item><item><uuid>598c1b4cc957455b84c2edcbe844e169</uuid><name>Input fail cause</name><type>SNMP_AGENT</type><snmp_oid>1.3.6.1.4.1.318.1.1.1.3.2.5.0</snmp_oid><key>input.fail[upsAdvInputLineFailCause]</key><history>7d</history><description>MIB: PowerNet-MIB
The reason for the occurrence of the last transfer to UPS
battery power.  The variable is set to:
- noTransfer(1) -- if there is no transfer yet.
- highLineVoltage(2) -- if the transfer to battery is caused
by an over voltage greater than the high transfer voltage.
- brownout(3) -- if the duration of the outage is greater than
five seconds and the line voltage is between 40% of the
rated output voltage and the low transfer voltage.
- blackout(4) -- if the duration of the outage is greater than five
seconds and the line voltage is between 40% of the rated
output voltage and ground.
- smallMomentarySag(5) -- if the duration of the outage is less
than five seconds and the line voltage is between 40% of the
rated output voltage and the low transfer voltage.
- deepMomentarySag(6) -- if the duration of the outage is less
than five seconds and the line voltage is between 40% of the
rated output voltage and ground.  The variable is set to
- smallMomentarySpike(7) -- if the line failure is caused by a
rate of change of input voltage less than ten volts per cycle.
- largeMomentarySpike(8) -- if the line failure is caused by
a rate of change of input voltage greater than ten volts per cycle.
- selfTest(9) -- if the UPS was commanded to do a self test.
- rateOfVoltageChange(10) -- if the failure is due to the rate of change of
the line voltage.</description><valuemap><name>PowerNet-MIB::upsAdvInputLineFailCause</name></valuemap><preprocessing><step><type>DISCARD_UNCHANGED_HEARTBEAT</type><parameters><parameter>6h</parameter></parameters></step></preprocessing><tags><tag><tag>component</tag><value>power</value></tag></tags></item><item><uuid>8ab48c798ac94773b37228a8f725efd0</uuid><name>Input frequency</name><type>SNMP_AGENT</type><snmp_oid>1.3.6.1.4.1.318.1.1.1.3.3.4.0</snmp_oid><key>input.frequency[upsHighPrecInputFrequency]</key><history>7d</history><value_type>FLOAT</value_type><units>Hz</units><description>MIB: PowerNet-MIB
The current input frequency to the UPS system in Hz.</description><preprocessing><step><type>MULTIPLIER</type><parameters><parameter>0.1</parameter></parameters></step><step><type>DISCARD_UNCHANGED_HEARTBEAT</type><parameters><parameter>6h</parameter></parameters></step></preprocessing><tags><tag><tag>component</tag><value>power</value></tag></tags><triggers><trigger><uuid>03b674d215604dc8acc3449610b05878</uuid><expression>min(/APC UPS Symmetra RX by SNMP/input.frequency[upsHighPrecInputFrequency],{$TIME.PERIOD}) &gt; 0 and (min(/APC UPS Symmetra RX by SNMP/input.frequency[upsHighPrecInputFrequency],{$TIME.PERIOD}) &gt; {$UPS.INPUT_FREQ.MAX.WARN} or max(/APC UPS Symmetra RX by SNMP/input.frequency[upsHighPrecInputFrequency],{$TIME.PERIOD}) &lt; {$UPS.INPUT_FREQ.MIN.WARN})</expression><name>Unacceptable input frequency</name><event_name>Unacceptable input frequency (out of range {$UPS.INPUT_FREQ.MIN.WARN}-{$UPS.INPUT_FREQ.MAX.WARN}Hz for {$TIME.PERIOD})</event_name><opdata>Current frequency: {ITEM.LASTVALUE1}</opdata><priority>HIGH</priority><tags><tag><tag>scope</tag><value>notice</value></tag></tags></trigger></triggers></item><item><uuid>5478b17ba84c4f12bc1ffa7dfc507ae1</uuid><name>Input voltage</name><type>SNMP_AGENT</type><snmp_oid>1.3.6.1.4.1.318.1.1.1.3.3.1.0</snmp_oid><key>input.voltage[upsHighPrecInputLineVoltage]</key><history>7d</history><value_type>FLOAT</value_type><units>V</units><description>MIB: PowerNet-MIB
The current utility line voltage in VAC.</description><preprocessing><step><type>MULTIPLIER</type><parameters><parameter>0.1</parameter></parameters></step><step><type>DISCARD_UNCHANGED_HEARTBEAT</type><parameters><parameter>6h</parameter></parameters></step></preprocessing><tags><tag><tag>component</tag><value>power</value></tag></tags><triggers><trigger><uuid>bf495f3ffefd4e65af488d91b360539c</uuid><expression>min(/APC UPS Symmetra RX by SNMP/input.voltage[upsHighPrecInputLineVoltage],{$TIME.PERIOD}) &gt; 0 and (min(/APC UPS Symmetra RX by SNMP/input.voltage[upsHighPrecInputLineVoltage],{$TIME.PERIOD}) &gt; {$UPS.INPUT_VOLT.MAX.WARN} or max(/APC UPS Symmetra RX by SNMP/input.voltage[upsHighPrecInputLineVoltage],{$TIME.PERIOD}) &lt; {$UPS.INPUT_VOLT.MIN.WARN})</expression><name>Unacceptable input voltage</name><event_name>Unacceptable input voltage (out of range {$UPS.INPUT_VOLT.MIN.WARN}-{$UPS.INPUT_VOLT.MAX.WARN}V for {$TIME.PERIOD})</event_name><opdata>Current voltage: {ITEM.LASTVALUE1}</opdata><priority>HIGH</priority><tags><tag><tag>scope</tag><value>notice</value></tag></tags></trigger></triggers></item><item><uuid>71cfc894a29f4bffb1f4199e0010aea0</uuid><name>Output current</name><type>SNMP_AGENT</type><snmp_oid>1.3.6.1.4.1.318.1.1.1.4.3.4.0</snmp_oid><key>output.current[upsHighPrecOutputCurrent]</key><history>7d</history><value_type>FLOAT</value_type><units>A</units><description>MIB: PowerNet-MIB
The current in amperes drawn by the load on the UPS.</description><preprocessing><step><type>MULTIPLIER</type><parameters><parameter>0.1</parameter></parameters></step><step><type>DISCARD_UNCHANGED_HEARTBEAT</type><parameters><parameter>6h</parameter></parameters></step></preprocessing><tags><tag><tag>component</tag><value>power</value></tag></tags></item><item><uuid>3ac052b6b4e241d9af470b70212ab8d3</uuid><name>Output load</name><type>SNMP_AGENT</type><snmp_oid>1.3.6.1.4.1.318.1.1.1.4.3.3.0</snmp_oid><key>output.load[upsHighPrecOutputLoad]</key><history>7d</history><value_type>FLOAT</value_type><units>%</units><description>MIB: PowerNet-MIB
The current UPS load expressed as percentage
of rated capacity.</description><preprocessing><step><type>MULTIPLIER</type><parameters><parameter>0.1</parameter></parameters></step><step><type>DISCARD_UNCHANGED_HEARTBEAT</type><parameters><parameter>6h</parameter></parameters></step></preprocessing><tags><tag><tag>component</tag><value>power</value></tag></tags><triggers><trigger><uuid>f2790aa869724c5bbeff6031561f2ca4</uuid><expression>min(/APC UPS Symmetra RX by SNMP/output.load[upsHighPrecOutputLoad],{$TIME.PERIOD}) &gt; {$UPS.OUTPUT.MAX.WARN}</expression><name>Output load is high</name><event_name>Output load is high (over {$UPS.OUTPUT.MAX.WARN}% for {$TIME.PERIOD})</event_name><opdata>Current load: {ITEM.LASTVALUE1}</opdata><priority>HIGH</priority><description>A battery installed has an internal error condition.</description><tags><tag><tag>scope</tag><value>notice</value></tag></tags></trigger></triggers></item><item><uuid>f8e4bcaa71e045e09af82ee739202778</uuid><name>Output status</name><type>SNMP_AGENT</type><snmp_oid>1.3.6.1.4.1.318.1.1.1.4.1.1.0</snmp_oid><key>output.status[upsBasicOutputStatus]</key><history>7d</history><description>MIB: PowerNet-MIB
The current state of the UPS. If the UPS is unable to
 determine the state of the UPS this variable is set
 to unknown(1).
During self-test most UPSes report onBattery(3) but
 some that support it will report onBatteryTest(15).
 To determine self-test status across all UPSes, refer
 to the upsBasicStateOutputState OID.</description><valuemap><name>PowerNet-MIB::upsBasicOutputStatus</name></valuemap><preprocessing><step><type>DISCARD_UNCHANGED_HEARTBEAT</type><parameters><parameter>6h</parameter></parameters></step></preprocessing><tags><tag><tag>component</tag><value>health</value></tag><tag><tag>component</tag><value>power</value></tag></tags><triggers><trigger><uuid>48a2bee152664ede98bed55c05cc437d</uuid><expression>last(/APC UPS Symmetra RX by SNMP/output.status[upsBasicOutputStatus])=16</expression><name>UPS is Emergency Static Bypass</name><priority>AVERAGE</priority><tags><tag><tag>scope</tag><value>notice</value></tag></tags></trigger><trigger><uuid>ccd80d5877e0401b8f56f22ca2da2f94</uuid><expression>last(/APC UPS Symmetra RX by SNMP/output.status[upsBasicOutputStatus])=10</expression><name>UPS is Hardware Failure Bypass</name><priority>AVERAGE</priority><tags><tag><tag>scope</tag><value>notice</value></tag></tags></trigger><trigger><uuid>e54fd69ac4354716a107d4d094b387f0</uuid><expression>last(/APC UPS Symmetra RX by SNMP/output.status[upsBasicOutputStatus])=7</expression><name>UPS is Off</name><priority>AVERAGE</priority><tags><tag><tag>scope</tag><value>notice</value></tag></tags></trigger><trigger><uuid>92df44ef170d471394f4cf8ff6882c39</uuid><expression>last(/APC UPS Symmetra RX by SNMP/output.status[upsBasicOutputStatus])=3</expression><name>UPS is on battery</name><priority>AVERAGE</priority><tags><tag><tag>scope</tag><value>notice</value></tag></tags></trigger><trigger><uuid>b6f6c160466e43d8b7f210b2efdd8ca3</uuid><expression>last(/APC UPS Symmetra RX by SNMP/output.status[upsBasicOutputStatus])=4</expression><name>UPS is on Smart Boost</name><priority>AVERAGE</priority><tags><tag><tag>scope</tag><value>notice</value></tag></tags></trigger><trigger><uuid>7d6323e1a03a48efb9f349ecd7e10153</uuid><expression>last(/APC UPS Symmetra RX by SNMP/output.status[upsBasicOutputStatus])=12</expression><name>UPS is On Smart Trim</name><priority>AVERAGE</priority><tags><tag><tag>scope</tag><value>notice</value></tag></tags></trigger><trigger><uuid>18a31f11313b47c8ab9e9cd4791c1532</uuid><expression>last(/APC UPS Symmetra RX by SNMP/output.status[upsBasicOutputStatus])=8</expression><name>UPS is Rebooting</name><priority>AVERAGE</priority><tags><tag><tag>scope</tag><value>notice</value></tag></tags></trigger><trigger><uuid>142e25b05d1547f0a683f6caee773ef5</uuid><expression>last(/APC UPS Symmetra RX by SNMP/output.status[upsBasicOutputStatus])=11</expression><name>UPS is Sleeping Until Power Return</name><priority>AVERAGE</priority><tags><tag><tag>scope</tag><value>notice</value></tag></tags></trigger><trigger><uuid>b6e22e8295c84fbebb8061c96ddd75f9</uuid><expression>last(/APC UPS Symmetra RX by SNMP/output.status[upsBasicOutputStatus])=6</expression><name>UPS is Software Bypass</name><priority>AVERAGE</priority><tags><tag><tag>scope</tag><value>notice</value></tag></tags></trigger><trigger><uuid>1c97c8ca6d6640fe829bf896f989bd91</uuid><expression>last(/APC UPS Symmetra RX by SNMP/output.status[upsBasicOutputStatus])=9</expression><name>UPS is Switched Bypass</name><priority>AVERAGE</priority><tags><tag><tag>scope</tag><value>notice</value></tag></tags></trigger><trigger><uuid>0683dbba9f4b4480ba15e040b8b83211</uuid><expression>last(/APC UPS Symmetra RX by SNMP/output.status[upsBasicOutputStatus])=5</expression><name>UPS is Timed Sleeping</name><priority>AVERAGE</priority><tags><tag><tag>scope</tag><value>notice</value></tag></tags></trigger></triggers></item><item><uuid>e7969358cce84f3eb749b1c43d96c583</uuid><name>Output voltage</name><type>SNMP_AGENT</type><snmp_oid>1.3.6.1.4.1.318.1.1.1.4.3.1.0</snmp_oid><key>output.voltage[upsHighPrecOutputVoltage]</key><history>7d</history><value_type>FLOAT</value_type><units>V</units><description>MIB: PowerNet-MIB
The output voltage of the UPS system in VAC.</description><preprocessing><step><type>MULTIPLIER</type><parameters><parameter>0.1</parameter></parameters></step><step><type>DISCARD_UNCHANGED_HEARTBEAT</type><parameters><parameter>6h</parameter></parameters></step></preprocessing><tags><tag><tag>component</tag><value>power</value></tag></tags></item><item><uuid>c892c7f2ddcd4e15b1d5ab907cd70dcf</uuid><name>SNMP traps (fallback)</name><type>SNMP_TRAP</type><key>snmptrap.fallback</key><history>2w</history><trends>0</trends><value_type>LOG</value_type><description>The item is used to collect all SNMP traps unmatched by other snmptrap items</description><logtimefmt>hh:mm:sszyyyy/MM/dd</logtimefmt><tags><tag><tag>component</tag><value>network</value></tag></tags></item><item><uuid>1de71b45323b4eb5bc1a38315d56ce58</uuid><name>System contact details</name><type>SNMP_AGENT</type><snmp_oid>1.3.6.1.2.1.1.4.0</snmp_oid><key>system.contact[sysContact.0]</key><delay>15m</delay><history>2w</history><trends>0</trends><value_type>CHAR</value_type><description>MIB: SNMPv2-MIB
The textual identification of the contact person for this managed
node, together with information on how to contact this person.  If no contact
information is known, the value is the zero-length string.</description><inventory_link>CONTACT</inventory_link><preprocessing><step><type>DISCARD_UNCHANGED_HEARTBEAT</type><parameters><parameter>12h</parameter></parameters></step></preprocessing><tags><tag><tag>component</tag><value>system</value></tag></tags></item><item><uuid>9bca97c1e308421b82f4769151f5177e</uuid><name>System description</name><type>SNMP_AGENT</type><snmp_oid>1.3.6.1.2.1.1.1.0</snmp_oid><key>system.descr[sysDescr.0]</key><delay>15m</delay><history>2w</history><trends>0</trends><value_type>CHAR</value_type><description>MIB: SNMPv2-MIB
A textual description of the entity. This value should
include the full name and version identification of the system's hardware type, software operating-system, and
networking software.</description><preprocessing><step><type>DISCARD_UNCHANGED_HEARTBEAT</type><parameters><parameter>12h</parameter></parameters></step></preprocessing><tags><tag><tag>component</tag><value>system</value></tag></tags></item><item><uuid>c7522be948bd4f97a47d59cf1e281c56</uuid><name>Uptime (hardware)</name><type>SNMP_AGENT</type><snmp_oid>1.3.6.1.2.1.25.1.1.0</snmp_oid><key>system.hw.uptime[hrSystemUptime.0]</key><delay>30s</delay><history>2w</history><trends>0d</trends><units>uptime</units><description>MIB: HOST-RESOURCES-MIB
The amount of time since this host was last initialized.
Note that this is different from sysUpTime in the SNMPv2-MIB
[RFC1907] because sysUpTime is the uptime of the
network management portion of the system.</description><preprocessing><step><type>CHECK_NOT_SUPPORTED</type><parameters><parameter/></parameters><error_handler>CUSTOM_VALUE</error_handler><error_handler_params>0</error_handler_params></step><step><type>MULTIPLIER</type><parameters><parameter>0.01</parameter></parameters></step></preprocessing><tags><tag><tag>component</tag><value>system</value></tag></tags></item><item><uuid>be1280a6b2d84393ad001113bf7c80f2</uuid><name>System location</name><type>SNMP_AGENT</type><snmp_oid>1.3.6.1.2.1.1.6.0</snmp_oid><key>system.location[sysLocation.0]</key><delay>15m</delay><history>2w</history><trends>0</trends><value_type>CHAR</value_type><description>MIB: SNMPv2-MIB
The physical location of this node (e.g., `telephone closet,
3rd floor').  If the location is unknown, the value is the zero-length string.</description><inventory_link>LOCATION</inventory_link><preprocessing><step><type>DISCARD_UNCHANGED_HEARTBEAT</type><parameters><parameter>6h</parameter></parameters></step></preprocessing><tags><tag><tag>component</tag><value>system</value></tag></tags></item><item><uuid>5c5b88814e4c4dc9b90ed4a5e49a91ca</uuid><name>Model</name><type>SNMP_AGENT</type><snmp_oid>1.3.6.1.4.1.318.1.1.1.1.1.1.0</snmp_oid><key>system.model[upsBasicIdentModel]</key><delay>15m</delay><history>7d</history><trends>0</trends><value_type>CHAR</value_type><description>MIB: PowerNet-MIB
The UPS model name (e.g. 'APC Smart-UPS 600').</description><preprocessing><step><type>DISCARD_UNCHANGED_HEARTBEAT</type><parameters><parameter>6h</parameter></parameters></step></preprocessing><tags><tag><tag>component</tag><value>inventory</value></tag></tags></item><item><uuid>3c521e1e94da4dd2bd71719bf20e14b8</uuid><name>System name</name><type>SNMP_AGENT</type><snmp_oid>1.3.6.1.2.1.1.5.0</snmp_oid><key>system.name[sysName.0]</key><delay>15m</delay><history>2w</history><trends>0</trends><value_type>CHAR</value_type><description>MIB: SNMPv2-MIB
An administratively-assigned name for this managed node.By
convention, this is the node's fully-qualified domain name.  If the name is unknown,
the value is the zero-length string.</description><inventory_link>NAME</inventory_link><preprocessing><step><type>DISCARD_UNCHANGED_HEARTBEAT</type><parameters><parameter>6h</parameter></parameters></step></preprocessing><tags><tag><tag>component</tag><value>system</value></tag></tags><triggers><trigger><uuid>5224767a1bee42738c49361ddabfed4b</uuid><expression>last(/APC UPS Symmetra RX by SNMP/system.name[sysName.0],#1)&lt;&gt;last(/APC UPS Symmetra RX by SNMP/system.name[sysName.0],#2) and length(last(/APC UPS Symmetra RX by SNMP/system.name[sysName.0]))&gt;0</expression><name>System name has changed</name><event_name>System name has changed (new name: {ITEM.VALUE})</event_name><priority>INFO</priority><description>System name has changed. Ack to close.</description><manual_close>YES</manual_close><tags><tag><tag>scope</tag><value>notice</value></tag><tag><tag>scope</tag><value>security</value></tag></tags></trigger></triggers></item><item><uuid>4aac942cab30432d81c4df32e01af5e2</uuid><name>Uptime (network)</name><type>SNMP_AGENT</type><snmp_oid>1.3.6.1.2.1.1.3.0</snmp_oid><key>system.net.uptime[sysUpTime.0]</key><delay>30s</delay><history>2w</history><trends>0d</trends><units>uptime</units><description>MIB: SNMPv2-MIB
The time (in hundredths of a second) since the network management
portion of the system was last re-initialized.</description><preprocessing><step><type>MULTIPLIER</type><parameters><parameter>0.01</parameter></parameters></step></preprocessing><tags><tag><tag>component</tag><value>system</value></tag></tags></item><item><uuid>0d3fcfce413a4f6aaaa2390183ab0c82</uuid><name>System object ID</name><type>SNMP_AGENT</type><snmp_oid>1.3.6.1.2.1.1.2.0</snmp_oid><key>system.objectid[sysObjectID.0]</key><delay>15m</delay><history>2w</history><trends>0</trends><value_type>CHAR</value_type><description>MIB: SNMPv2-MIB
The vendor's authoritative identification of the network management
subsystem contained in the entity.  This value is allocated within the SMI enterprises
subtree (1.3.6.1.4.1) and provides an easy and unambiguous means for determining`what
kind of box' is being managed.  For example, if vendor`Flintstones, Inc.' was
assigned the subtree1.3.6.1.4.1.4242, it could assign the identifier 1.3.6.1.4.1.4242.1.1
to its `Fred Router'.</description><preprocessing><step><type>DISCARD_UNCHANGED_HEARTBEAT</type><parameters><parameter>6h</parameter></parameters></step></preprocessing><tags><tag><tag>component</tag><value>system</value></tag></tags></item><item><uuid>0e72609b44094aff8acfa58b63ca97ba</uuid><name>Serial number</name><type>SNMP_AGENT</type><snmp_oid>1.3.6.1.4.1.318.1.1.1.1.2.3.0</snmp_oid><key>system.sn[upsAdvIdentSerialNumber]</key><delay>15m</delay><history>7d</history><trends>0</trends><value_type>CHAR</value_type><description>MIB: PowerNet-MIB
An 8-character string identifying the serial number of
 the UPS internal microprocessor.  This number is set at
 the factory.  NOTE: This number does NOT correspond to
 the serial number on the rear of the UPS.</description><preprocessing><step><type>DISCARD_UNCHANGED_HEARTBEAT</type><parameters><parameter>6h</parameter></parameters></step></preprocessing><tags><tag><tag>component</tag><value>inventory</value></tag></tags></item><item><uuid>582ff80b2df049b8acf233ad4dbfe1f1</uuid><name>SNMP agent availability</name><type>INTERNAL</type><key>zabbix[host,snmp,available]</key><history>7d</history><description>Availability of SNMP checks on the host. The value of this item corresponds to availability icons in the host list.
Possible value:
0 - not available
1 - available
2 - unknown</description><valuemap><name>zabbix.host.available</name></valuemap><preprocessing><step><type>DISCARD_UNCHANGED_HEARTBEAT</type><parameters><parameter>6h</parameter></parameters></step></preprocessing><tags><tag><tag>component</tag><value>health</value></tag><tag><tag>component</tag><value>network</value></tag></tags><triggers><trigger><uuid>c0ad0941746546aeb6de2fee087c8252</uuid><expression>max(/APC UPS Symmetra RX by SNMP/zabbix[host,snmp,available],{$SNMP.TIMEOUT})=0</expression><name>No SNMP data collection</name><opdata>Current state: {ITEM.LASTVALUE1}</opdata><priority>WARNING</priority><description>SNMP is not available for polling. Please check device connectivity and SNMP settings.</description><tags><tag><tag>scope</tag><value>availability</value></tag></tags></trigger></triggers></item></items><discovery_rules><discovery_rule><uuid>eddb568fd0e34398bcee7d39a6f76319</uuid><name>External bad battery packs discovery</name><type>SNMP_AGENT</type><snmp_oid>discovery[{#EXTERNAL_PACKS},1.3.6.1.4.1.318.1.1.1.2.2.6]</snmp_oid><key>battery.packs.bad.discovery</key><delay>1h</delay><description>Discovery of the number of external defective battery packs.</description><item_prototypes><item_prototype><uuid>11c16d0e18a745679bcf8546cb8f0641</uuid><name>{#SNMPINDEX}: External battery packs bad</name><type>SNMP_AGENT</type><snmp_oid>1.3.6.1.4.1.318.1.1.1.2.2.6.0</snmp_oid><key>battery.external_packs_bad[upsAdvBatteryNumOfBadBattPacks.{#SNMPINDEX}]</key><delay>15m</delay><history>7d</history><description>MIB: PowerNet-MIB
The number of external battery packs connected to the UPS that
are defective. If the UPS does not use smart cells then the
agent reports ERROR_NO_SUCH_NAME.</description><preprocessing><step><type>DISCARD_UNCHANGED_HEARTBEAT</type><parameters><parameter>6h</parameter></parameters></step></preprocessing><tags><tag><tag>component</tag><value>inventory</value></tag></tags></item_prototype></item_prototypes></discovery_rule><discovery_rule><uuid>0c31de1650b94f8cabef339e2ef009e3</uuid><name>External battery packs discovery</name><type>SNMP_AGENT</type><snmp_oid>discovery[{#CARTRIDGE_STATUS},1.3.6.1.4.1.318.1.1.1.2.3.10.2.1.7,{#BATTERY_PACK},1.3.6.1.4.1.318.1.1.1.2.3.10.2.1.1,{#CARTRIDGE_INDEX},1.3.6.1.4.1.318.1.1.1.2.3.10.2.1.2]</snmp_oid><key>battery.packs.discovery</key><delay>1h</delay><filter><evaltype>AND</evaltype><conditions><condition><macro>{#CARTRIDGE_STATUS}</macro><value>^$</value><operator>NOT_MATCHES_REGEX</operator><formulaid>A</formulaid></condition></conditions></filter><item_prototypes><item_prototype><uuid>6bd2d90f306e4252b5fc44eab860f4ab</uuid><name>{#BATTERY_PACK}.{#CARTRIDGE_INDEX}: Battery estimated replace date</name><type>SNMP_AGENT</type><snmp_oid>1.3.6.1.4.1.318.1.1.1.2.3.10.2.1.8.{#SNMPINDEX}</snmp_oid><key>battery.estimated_replace_date[upsHighPrecBatteryPackCartridgeReplaceDate.{#BATTERY_PACK}.{#CARTRIDGE_INDEX}]</key><delay>1h</delay><history>7d</history><trends>0</trends><value_type>CHAR</value_type><description>MIB: PowerNet-MIB
The battery cartridge estimated battery replace date.</description><preprocessing><step><type>DISCARD_UNCHANGED_HEARTBEAT</type><parameters><parameter>6h</parameter></parameters></step></preprocessing><tags><tag><tag>component</tag><value>inventory</value></tag><tag><tag>component</tag><value>power</value></tag></tags></item_prototype><item_prototype><uuid>c4a7061be8f64f398ad0f3c52db29bbd</uuid><name>{#BATTERY_PACK}.{#CARTRIDGE_INDEX}: Battery pack cartridge health</name><type>SNMP_AGENT</type><snmp_oid>1.3.6.1.4.1.318.1.1.1.2.3.10.2.1.7.{#SNMPINDEX}</snmp_oid><key>battery.pack.cartridge_health[upsHighPrecBatteryPackCartridgeHealth.{#BATTERY_PACK}.{#CARTRIDGE_INDEX}]</key><history>7d</history><trends>0</trends><value_type>CHAR</value_type><description>MIB: PowerNet-MIB
The battery cartridge health.
  bit 0 Battery lifetime okay
  bit 1 Battery lifetime near end, order replacement cartridge
  bit 2 Battery lifetime exceeded, replace battery
  bit 3 Battery lifetime near end acknowledged, order replacement cartridge
  bit 4 Battery lifetime exceeded acknowledged, replace battery
  bit 5 Battery measured lifetime near end, order replacement cartridge
  bit 6 Battery measured lifetime near end acknowledged, order replacement cartridge</description><preprocessing><step><type>DISCARD_UNCHANGED_HEARTBEAT</type><parameters><parameter>6h</parameter></parameters></step></preprocessing><tags><tag><tag>component</tag><value>health</value></tag><tag><tag>component</tag><value>power</value></tag></tags><trigger_prototypes><trigger_prototype><uuid>3a48257337a84a2296db92410a8aed8c</uuid><expression>find(/APC UPS Symmetra RX by SNMP/battery.pack.cartridge_health[upsHighPrecBatteryPackCartridgeHealth.{#BATTERY_PACK}.{#CARTRIDGE_INDEX}],,&quot;regexp&quot;,&quot;^(0)[0|1]{15}$&quot;)=1</expression><name>{#BATTERY_PACK}.{#CARTRIDGE_INDEX}: Battery lifetime is not okay</name><opdata>Current bit set: {ITEM.LASTVALUE1}</opdata><priority>WARNING</priority><description>The battery cartridge health.
  bit 0 Battery lifetime okay
  bit 1 Battery lifetime near end, order replacement cartridge
  bit 2 Battery lifetime exceeded, replace battery
  bit 3 Battery lifetime near end acknowledged, order replacement cartridge
  bit 4 Battery lifetime exceeded acknowledged, replace battery
  bit 5 Battery measured lifetime near end, order replacement cartridge
  bit 6 Battery measured lifetime near end acknowledged, order replacement cartridge</description><tags><tag><tag>scope</tag><value>notice</value></tag></tags></trigger_prototype></trigger_prototypes></item_prototype><item_prototype><uuid>8f5b3a61acad491f8ca6860f6201252d</uuid><name>{#BATTERY_PACK}.{#CARTRIDGE_INDEX}: Battery status</name><type>SNMP_AGENT</type><snmp_oid>1.3.6.1.4.1.318.1.1.1.2.3.10.2.1.10.{#SNMPINDEX}</snmp_oid><key>battery.pack.status[upsHighPrecBatteryPackCartridgeStatus.{#BATTERY_PACK}.{#CARTRIDGE_INDEX}]</key><history>7d</history><trends>0</trends><value_type>CHAR</value_type><description>MIB: PowerNet-MIB
The battery cartridge status.
bit 0 Disconnected
bit 1 Overvoltage
bit 2 NeedsReplacement
bit 3 OvertemperatureCritical
bit 4 Charger
bit 5 TemperatureSensor
bit 6 BusSoftStart
bit 7 OvertemperatureWarning
bit 8 GeneralError
bit 9 Communication
bit 10 DisconnectedFrame
bit 11 FirmwareMismatch</description><preprocessing><step><type>DISCARD_UNCHANGED_HEARTBEAT</type><parameters><parameter>6h</parameter></parameters></step></preprocessing><tags><tag><tag>component</tag><value>health</value></tag><tag><tag>component</tag><value>power</value></tag></tags><trigger_prototypes><trigger_prototype><uuid>4498d376328e405bad7da5f1832cde8a</uuid><expression>find(/APC UPS Symmetra RX by SNMP/battery.pack.status[upsHighPrecBatteryPackCartridgeStatus.{#BATTERY_PACK}.{#CARTRIDGE_INDEX}],,&quot;regexp&quot;,&quot;^(0{16})$&quot;)=0</expression><name>{#BATTERY_PACK}.{#CARTRIDGE_INDEX}: Battery status is not okay</name><opdata>Current bit set: {ITEM.LASTVALUE1}</opdata><priority>WARNING</priority><description>The battery cartridge status:
bit 0 Disconnected
bit 1 Overvoltage
bit 2 NeedsReplacement
bit 3 OvertemperatureCritical
bit 4 Charger
bit 5 TemperatureSensor
bit 6 BusSoftStart
bit 7 OvertemperatureWarning
bit 8 GeneralError
bit 9 Communication
bit 10 DisconnectedFrame
bit 11 FirmwareMismatch</description><tags><tag><tag>scope</tag><value>notice</value></tag></tags></trigger_prototype></trigger_prototypes></item_prototype><item_prototype><uuid>346f2ab5b340401880c63a6cb9eec949</uuid><name>{#BATTERY_PACK}.{#CARTRIDGE_INDEX}: Battery temperature</name><type>SNMP_AGENT</type><snmp_oid>1.3.6.1.4.1.318.1.1.1.2.3.10.2.1.5.{#SNMPINDEX}</snmp_oid><key>battery.temperature[upsHighPrecBatteryPackTemperature.{#BATTERY_PACK}.{#CARTRIDGE_INDEX}]</key><history>7d</history><value_type>FLOAT</value_type><units>℃</units><description>MIB: PowerNet-MIB
The battery pack temperature in Celsius.</description><preprocessing><step><type>MULTIPLIER</type><parameters><parameter>0.1</parameter></parameters></step><step><type>DISCARD_UNCHANGED_HEARTBEAT</type><parameters><parameter>6h</parameter></parameters></step></preprocessing><tags><tag><tag>component</tag><value>temperature</value></tag></tags><trigger_prototypes><trigger_prototype><uuid>f710e2b952054f35ab6e3e8e90ab7f83</uuid><expression>min(/APC UPS Symmetra RX by SNMP/battery.temperature[upsHighPrecBatteryPackTemperature.{#BATTERY_PACK}.{#CARTRIDGE_INDEX}],{$TIME.PERIOD}) &gt; {$BATTERY.TEMP.MAX.WARN}</expression><name>{#BATTERY_PACK}.{#CARTRIDGE_INDEX}: Battery has high temperature</name><event_name>{#BATTERY_PACK}.{#CARTRIDGE_INDEX}: Battery has high temperature (over {$BATTERY.TEMP.MAX.WARN}℃ for {$TIME.PERIOD})</event_name><opdata>Current temperature: {ITEM.LASTVALUE1}</opdata><priority>HIGH</priority><tags><tag><tag>scope</tag><value>notice</value></tag></tags></trigger_prototype></trigger_prototypes></item_prototype><item_prototype><uuid>230fc138d8f64c4f9eeee438d42b519e</uuid><name>{#BATTERY_PACK}.{#CARTRIDGE_INDEX}: Serial number</name><type>SNMP_AGENT</type><snmp_oid>1.3.6.1.4.1.318.1.1.1.2.3.10.2.1.4.{#SNMPINDEX}</snmp_oid><key>system.sn[upsHighPrecBatteryPackSerialNumber.{#BATTERY_PACK}.{#CARTRIDGE_INDEX}]</key><delay>15m</delay><history>7d</history><trends>0</trends><value_type>CHAR</value_type><description>MIB: PowerNet-MIB
The battery pack serial number.</description><preprocessing><step><type>DISCARD_UNCHANGED_HEARTBEAT</type><parameters><parameter>6h</parameter></parameters></step></preprocessing><tags><tag><tag>component</tag><value>inventory</value></tag></tags></item_prototype></item_prototypes></discovery_rule><discovery_rule><uuid>93941e38fd2d4b48bd8b50179692cb56</uuid><name>External sensor port 1 discovery</name><type>SNMP_AGENT</type><snmp_oid>discovery[{#EXTERNAL_SENSOR1_NAME},1.3.6.1.4.1.318.1.1.25.1.2.1.3]</snmp_oid><key>external.sensor1.discovery</key><delay>1h</delay><description>uioSensorStatusTable</description><item_prototypes><item_prototype><uuid>15f23c88f9b24580add63b69fb8a41de</uuid><name>{#EXTERNAL_SENSOR1_NAME}: Humidity sensor</name><type>SNMP_AGENT</type><snmp_oid>1.3.6.1.4.1.318.1.1.25.1.2.1.7.1.1</snmp_oid><key>external.sensor.humidity[uioSensorStatusHumidity.1.{#SNMPINDEX}]</key><history>7d</history><value_type>FLOAT</value_type><units>%</units><description>MIB: PowerNet-MIB
The sensor's current humidity reading - a relative humidity
 percentage. -1 indicates an invalid reading due to either a
 sensor that doesn't read humidity or lost communications.</description><preprocessing><step><type>DISCARD_UNCHANGED_HEARTBEAT</type><parameters><parameter>6h</parameter></parameters></step></preprocessing><tags><tag><tag>component</tag><value>humidity</value></tag><tag><tag>component</tag><value>power</value></tag></tags></item_prototype><item_prototype><uuid>230f3e596bbc4cb6961eda599da74f5e</uuid><name>{#EXTERNAL_SENSOR1_NAME}: Sensor alarm status</name><type>SNMP_AGENT</type><snmp_oid>1.3.6.1.4.1.318.1.1.25.1.2.1.9.1.1</snmp_oid><key>external.sensor.status[uioSensorStatusAlarmStatus.1.{#SNMPINDEX}]</key><history>7d</history><description>MIB: PowerNet-MIB
The alarm status of the sensor. Possible values:
uioNormal                 (1),
uioWarning                (2),
uioCritical               (3),
sensorStatusNotApplicable (4)</description><valuemap><name>PowerNet-MIB::uioSensorStatusAlarmStatus</name></valuemap><preprocessing><step><type>DISCARD_UNCHANGED_HEARTBEAT</type><parameters><parameter>6h</parameter></parameters></step></preprocessing><tags><tag><tag>component</tag><value>health</value></tag><tag><tag>component</tag><value>power</value></tag></tags><trigger_prototypes><trigger_prototype><uuid>0de21ba7495d41f4834170122620c37d</uuid><expression>last(/APC UPS Symmetra RX by SNMP/external.sensor.status[uioSensorStatusAlarmStatus.1.{#SNMPINDEX}])=3</expression><name>{#EXTERNAL_SENSOR1_NAME}: Sensor has status Critical</name><priority>HIGH</priority><description>The external sensor has returned a value greater than the critical threshold.</description><tags><tag><tag>scope</tag><value>notice</value></tag></tags></trigger_prototype><trigger_prototype><uuid>69fbc11262f74fdfb49da43bb59c1810</uuid><expression>last(/APC UPS Symmetra RX by SNMP/external.sensor.status[uioSensorStatusAlarmStatus.1.{#SNMPINDEX}])=4</expression><name>{#EXTERNAL_SENSOR1_NAME}: Sensor has status Not Applicable</name><priority>INFO</priority><description>The external sensor does not work or is not connected.</description><tags><tag><tag>scope</tag><value>notice</value></tag></tags></trigger_prototype><trigger_prototype><uuid>0ce46cad353c4299ad5540a831b5c467</uuid><expression>last(/APC UPS Symmetra RX by SNMP/external.sensor.status[uioSensorStatusAlarmStatus.1.{#SNMPINDEX}])=2</expression><name>{#EXTERNAL_SENSOR1_NAME}: Sensor has status Warning</name><priority>AVERAGE</priority><description>The external sensor has returned a value greater than the warning threshold.</description><tags><tag><tag>scope</tag><value>notice</value></tag></tags></trigger_prototype></trigger_prototypes></item_prototype><item_prototype><uuid>f777176e1d7b4e328209aeeced8e680b</uuid><name>{#EXTERNAL_SENSOR1_NAME}: Temperature sensor</name><type>SNMP_AGENT</type><snmp_oid>1.3.6.1.4.1.318.1.1.25.1.2.1.6.1.1</snmp_oid><key>external.sensor.temperature[uioSensorStatusTemperatureDegC.1.{#SNMPINDEX}]</key><history>7d</history><value_type>FLOAT</value_type><units>℃</units><description>MIB: PowerNet-MIB
The sensor's current temperature reading in Celsius.
 -1 indicates an invalid reading due to lost communications.</description><preprocessing><step><type>DISCARD_UNCHANGED_HEARTBEAT</type><parameters><parameter>6h</parameter></parameters></step></preprocessing><tags><tag><tag>component</tag><value>power</value></tag><tag><tag>component</tag><value>temperature</value></tag></tags></item_prototype></item_prototypes><overrides><override><name>Temp</name><step>1</step><filter><conditions><condition><macro>{#EXTERNAL_SENSOR1_NAME}</macro><value>Temp</value><formulaid>A</formulaid></condition></conditions></filter><operations><operation><operationobject>ITEM_PROTOTYPE</operationobject><operator>LIKE</operator><value>Humidity</value><discover>NO_DISCOVER</discover></operation></operations></override></overrides></discovery_rule><discovery_rule><uuid>7cd4c33584004a6d811478e8a83e0898</uuid><name>External sensor port 2 discovery</name><type>SNMP_AGENT</type><snmp_oid>discovery[{#EXTERNAL_SENSOR2_NAME},1.3.6.1.4.1.318.1.1.25.1.2.2.3]</snmp_oid><key>external.sensor2.discovery</key><delay>1h</delay><description>uioSensorStatusTable</description><item_prototypes><item_prototype><uuid>3a933ac0f9b2425d9929ed244a3ce61a</uuid><name>{#EXTERNAL_SENSOR2_NAME}: Humidity sensor</name><type>SNMP_AGENT</type><snmp_oid>1.3.6.1.4.1.318.1.1.25.1.2.2.7.1.1</snmp_oid><key>external.sensor.humidity[uioSensorStatusHumidity.2.{#SNMPINDEX}]</key><history>7d</history><value_type>FLOAT</value_type><units>%</units><description>MIB: PowerNet-MIB
The sensor's current humidity reading - a relative humidity
 percentage. -1 indicates an invalid reading due to either a
 sensor that doesn't read humidity or lost communications.</description><preprocessing><step><type>DISCARD_UNCHANGED_HEARTBEAT</type><parameters><parameter>6h</parameter></parameters></step></preprocessing><tags><tag><tag>component</tag><value>humidity</value></tag><tag><tag>component</tag><value>power</value></tag></tags></item_prototype><item_prototype><uuid>b8a37686d5374b4fa05717987e54c2f6</uuid><name>{#EXTERNAL_SENSOR2_NAME}: Sensor alarm status</name><type>SNMP_AGENT</type><snmp_oid>1.3.6.1.4.1.318.1.1.25.1.2.2.9.1.1</snmp_oid><key>external.sensor.status[uioSensorStatusAlarmStatus.2.{#SNMPINDEX}]</key><history>7d</history><description>MIB: PowerNet-MIB
The alarm status of the sensor. Possible values:
uioNormal                 (1),
uioWarning                (2),
uioCritical               (3),
sensorStatusNotApplicable (4)</description><valuemap><name>PowerNet-MIB::uioSensorStatusAlarmStatus</name></valuemap><preprocessing><step><type>DISCARD_UNCHANGED_HEARTBEAT</type><parameters><parameter>6h</parameter></parameters></step></preprocessing><tags><tag><tag>component</tag><value>health</value></tag><tag><tag>component</tag><value>power</value></tag></tags><trigger_prototypes><trigger_prototype><uuid>f27f80f391a04927bb138ba66d48d364</uuid><expression>last(/APC UPS Symmetra RX by SNMP/external.sensor.status[uioSensorStatusAlarmStatus.2.{#SNMPINDEX}])=3</expression><name>{#EXTERNAL_SENSOR2_NAME}: Sensor has status Critical</name><priority>HIGH</priority><description>The external sensor has returned a value greater than the critical threshold.</description><tags><tag><tag>scope</tag><value>notice</value></tag></tags></trigger_prototype><trigger_prototype><uuid>a84e1b5140b643ad8bee020d74821255</uuid><expression>last(/APC UPS Symmetra RX by SNMP/external.sensor.status[uioSensorStatusAlarmStatus.2.{#SNMPINDEX}])=4</expression><name>{#EXTERNAL_SENSOR2_NAME}: Sensor has status Not Applicable</name><priority>INFO</priority><description>The external sensor does not work or is not connected.</description><tags><tag><tag>scope</tag><value>notice</value></tag></tags></trigger_prototype><trigger_prototype><uuid>b67ed4a3ce5a49e4ac4079e258d7fe7c</uuid><expression>last(/APC UPS Symmetra RX by SNMP/external.sensor.status[uioSensorStatusAlarmStatus.2.{#SNMPINDEX}])=2</expression><name>{#EXTERNAL_SENSOR2_NAME}: Sensor has status Warning</name><priority>AVERAGE</priority><description>The external sensor has returned a value greater than the warning threshold.</description><tags><tag><tag>scope</tag><value>notice</value></tag></tags></trigger_prototype></trigger_prototypes></item_prototype><item_prototype><uuid>15e3cf28f89043029e722b1813737c6c</uuid><name>{#EXTERNAL_SENSOR2_NAME}: Temperature sensor</name><type>SNMP_AGENT</type><snmp_oid>1.3.6.1.4.1.318.1.1.25.1.2.2.6.1.1</snmp_oid><key>external.sensor.temperature[uioSensorStatusTemperatureDegC.2.{#SNMPINDEX}]</key><history>7d</history><value_type>FLOAT</value_type><units>℃</units><description>MIB: PowerNet-MIB
The sensor's current temperature reading in Celsius.
 -1 indicates an invalid reading due to lost communications.</description><preprocessing><step><type>DISCARD_UNCHANGED_HEARTBEAT</type><parameters><parameter>6h</parameter></parameters></step></preprocessing><tags><tag><tag>component</tag><value>power</value></tag><tag><tag>component</tag><value>temperature</value></tag></tags></item_prototype></item_prototypes><overrides><override><name>Temp</name><step>1</step><filter><conditions><condition><macro>{#EXTERNAL_SENSOR2_NAME}</macro><value>Temp</value><formulaid>A</formulaid></condition></conditions></filter><operations><operation><operationobject>ITEM_PROTOTYPE</operationobject><operator>LIKE</operator><value>Humidity</value><discover>NO_DISCOVER</discover></operation></operations></override></overrides></discovery_rule><discovery_rule><uuid>88032aa9a832464ca2a077271113e7c9</uuid><name>Input phases discovery</name><type>SNMP_AGENT</type><snmp_oid>discovery[{#PHASEINDEX},1.3.6.1.4.1.318.1.1.1.9.2.3.1.2.1.1]</snmp_oid><key>input.phases.discovery</key><delay>1h</delay><description>The input phase identifier. OID upsPhaseInputPhaseIndex.1.1</description><item_prototypes><item_prototype><uuid>d6afc20571ce43fa9861ef6c1e17d6c8</uuid><name>{#PHASEINDEX}: Phase input current</name><type>SNMP_AGENT</type><snmp_oid>1.3.6.1.4.1.318.1.1.1.9.2.3.1.6.1.1.{#PHASEINDEX}</snmp_oid><key>phase.input.current[upsPhaseInputCurrent.1.1.{#PHASEINDEX}]</key><history>7d</history><value_type>FLOAT</value_type><units>A</units><description>MIB: PowerNet-MIB
The input current in 0.1 amperes, or -0.1 if it's
 unsupported by this UPS.</description><preprocessing><step><type>MULTIPLIER</type><parameters><parameter>0.1</parameter></parameters></step><step><type>DISCARD_UNCHANGED_HEARTBEAT</type><parameters><parameter>6h</parameter></parameters></step></preprocessing><tags><tag><tag>component</tag><value>power</value></tag></tags></item_prototype><item_prototype><uuid>6993631adffb41fabc7995bd9158e448</uuid><name>{#PHASEINDEX}: Phase input voltage</name><type>SNMP_AGENT</type><snmp_oid>1.3.6.1.4.1.318.1.1.1.9.2.3.1.3.1.1.{#PHASEINDEX}</snmp_oid><key>phase.input.voltage[upsPhaseInputVoltage.1.1.{#PHASEINDEX}]</key><history>7d</history><value_type>FLOAT</value_type><units>V</units><description>MIB: PowerNet-MIB
The input voltage in VAC, or -1 if it's unsupported
 by this UPS.</description><preprocessing><step><type>DISCARD_UNCHANGED_HEARTBEAT</type><parameters><parameter>6h</parameter></parameters></step></preprocessing><tags><tag><tag>component</tag><value>power</value></tag></tags><trigger_prototypes><trigger_prototype><uuid>212cf86650fc4c189115da565111f5d3</uuid><expression>min(/APC UPS Symmetra RX by SNMP/phase.input.voltage[upsPhaseInputVoltage.1.1.{#PHASEINDEX}],{$TIME.PERIOD}) &gt; {$UPS.INPUT_VOLT.MAX.WARN} or max(/APC UPS Symmetra RX by SNMP/phase.input.voltage[upsPhaseInputVoltage.1.1.{#PHASEINDEX}],{$TIME.PERIOD}) &lt; {$UPS.INPUT_VOLT.MIN.WARN}</expression><name>{#PHASEINDEX}: Unacceptable phase {#PHASEINDEX} input voltage</name><event_name>{#PHASEINDEX}: Unacceptable phase {#PHASEINDEX} input voltage (out of range {$UPS.INPUT_VOLT.MIN.WARN}-{$UPS.INPUT_VOLT.MAX.WARN}V for {$TIME.PERIOD})</event_name><opdata>Current phase {#PHASEINDEX} voltage: {ITEM.LASTVALUE1}</opdata><priority>HIGH</priority><tags><tag><tag>scope</tag><value>notice</value></tag></tags></trigger_prototype></trigger_prototypes></item_prototype></item_prototypes></discovery_rule><discovery_rule><uuid>262343758e9649a8a6fe2b77631f66df</uuid><name>Output phases discovery</name><type>SNMP_AGENT</type><snmp_oid>discovery[{#PHASEINDEX},1.3.6.1.4.1.318.1.1.1.9.3.3.1.2.1.1]</snmp_oid><key>output.phases.discovery</key><delay>1h</delay><description>The output phase identifier. OID upsPhaseOutputPhaseIndex.1.1</description><item_prototypes><item_prototype><uuid>6bed63601e6b426799b860dc5e2ea8b2</uuid><name>{#PHASEINDEX}: Phase output current</name><type>SNMP_AGENT</type><snmp_oid>1.3.6.1.4.1.318.1.1.1.9.3.3.1.4.1.1.{#PHASEINDEX}</snmp_oid><key>phase.output.current[upsPhaseOutputCurrent.1.1.{#PHASEINDEX}]</key><history>7d</history><value_type>FLOAT</value_type><units>A</units><description>MIB: PowerNet-MIB
The output current in 0.1 amperes drawn
 by the load on the UPS, or -1 if it's unsupported
 by this UPS.</description><preprocessing><step><type>MULTIPLIER</type><parameters><parameter>0.1</parameter></parameters></step><step><type>DISCARD_UNCHANGED_HEARTBEAT</type><parameters><parameter>6h</parameter></parameters></step></preprocessing><tags><tag><tag>component</tag><value>power</value></tag></tags></item_prototype><item_prototype><uuid>5ec8aae1e2b24350b005d0177b164e6b</uuid><name>{#PHASEINDEX}: Phase output load, %</name><type>SNMP_AGENT</type><snmp_oid>1.3.6.1.4.1.318.1.1.1.9.3.3.1.10.1.1.{#PHASEINDEX}</snmp_oid><key>phase.output.load.percent[upsPhaseOutputPercentLoad.1.1.{#PHASEINDEX}]</key><history>7d</history><value_type>FLOAT</value_type><units>%</units><description>MIB: PowerNet-MIB
The percentage of the UPS load capacity in VA at
 redundancy @ (n + x) presently being used on this
 output phase, or -1 if it's unsupported by this UPS.</description><preprocessing><step><type>DISCARD_UNCHANGED_HEARTBEAT</type><parameters><parameter>6h</parameter></parameters></step></preprocessing><tags><tag><tag>component</tag><value>power</value></tag></tags></item_prototype><item_prototype><uuid>3da95223adfc4d638406c6908bba7063</uuid><name>{#PHASEINDEX}: Phase output voltage</name><type>SNMP_AGENT</type><snmp_oid>1.3.6.1.4.1.318.1.1.1.9.3.3.1.3.1.1.{#PHASEINDEX}</snmp_oid><key>phase.output.voltage[upsPhaseOutputVoltage.1.1.{#PHASEINDEX}]</key><history>7d</history><value_type>FLOAT</value_type><units>V</units><description>MIB: PowerNet-MIB
The output voltage in VAC, or -1 if it's unsupported
 by this UPS.</description><preprocessing><step><type>DISCARD_UNCHANGED_HEARTBEAT</type><parameters><parameter>6h</parameter></parameters></step></preprocessing><tags><tag><tag>component</tag><value>power</value></tag></tags><trigger_prototypes><trigger_prototype><uuid>47069f8d431f45d490674d7ba01d2bb2</uuid><expression>min(/APC UPS Symmetra RX by SNMP/phase.output.voltage[upsPhaseOutputVoltage.1.1.{#PHASEINDEX}],{$TIME.PERIOD}) &gt; {$UPS.INPUT_VOLT.MAX.WARN} or max(/APC UPS Symmetra RX by SNMP/phase.output.voltage[upsPhaseOutputVoltage.1.1.{#PHASEINDEX}],{$TIME.PERIOD}) &lt; {$UPS.INPUT_VOLT.MIN.WARN}</expression><name>{#PHASEINDEX}: Unacceptable phase {#PHASEINDEX} output voltage</name><event_name>{#PHASEINDEX}: Unacceptable phase {#PHASEINDEX} output voltage (out of range {$UPS.INPUT_VOLT.MIN.WARN}-{$UPS.INPUT_VOLT.MAX.WARN}V for {$TIME.PERIOD})</event_name><opdata>Current phase {#PHASEINDEX} voltage: {ITEM.LASTVALUE1}</opdata><priority>HIGH</priority><tags><tag><tag>scope</tag><value>notice</value></tag></tags></trigger_prototype></trigger_prototypes></item_prototype></item_prototypes></discovery_rule></discovery_rules><tags><tag><tag>class</tag><value>power</value></tag><tag><tag>target</tag><value>apc</value></tag><tag><tag>target</tag><value>apc-ups-symmetra-rx</value></tag></tags><macros><macro><macro>{$BATTERY.CAPACITY.MIN.WARN}</macro><value>50</value><description>Minimum battery capacity percentage for trigger expression.</description></macro><macro><macro>{$BATTERY.TEMP.MAX.WARN}</macro><value>55</value><description>Maximum battery temperature for trigger expression.</description></macro><macro><macro>{$SNMP.TIMEOUT}</macro><value>5m</value><description>The time interval for SNMP agent availability trigger expression.</description></macro><macro><macro>{$TIME.PERIOD}</macro><value>15m</value><description>Time period for trigger expression.</description></macro><macro><macro>{$UPS.INPUT_FREQ.MAX.WARN}</macro><value>50.3</value><description>Maximum input frequency for trigger expression.</description></macro><macro><macro>{$UPS.INPUT_FREQ.MIN.WARN}</macro><value>49.7</value><description>Minimum input frequency for trigger expression.</description></macro><macro><macro>{$UPS.INPUT_VOLT.MAX.WARN}</macro><value>243</value><description>Maximum input voltage for trigger expression.</description></macro><macro><macro>{$UPS.INPUT_VOLT.MIN.WARN}</macro><value>197</value><description>Minimum input voltage for trigger expression.</description></macro><macro><macro>{$UPS.OUTPUT.MAX.WARN}</macro><value>80</value><description>Maximum output load in % for trigger expression.</description></macro></macros><dashboards><dashboard><uuid>6819b4e7963340438675de6c3f72bb4f</uuid><name>UPS Summary</name><pages><page><widgets><widget><type>PLAIN_TEXT</type><width>8</width><height>5</height><fields><field><type>ITEM</type><name>itemids</name><value><host>APC UPS Symmetra RX by SNMP</host><key>system.net.uptime[sysUpTime.0]</key></value></field></fields></widget><widget><type>PLAIN_TEXT</type><x>8</x><width>8</width><height>5</height><fields><field><type>ITEM</type><name>itemids</name><value><host>APC UPS Symmetra RX by SNMP</host><key>input.fail[upsAdvInputLineFailCause]</key></value></field></fields></widget><widget><type>PLAIN_TEXT</type><x>16</x><width>8</width><height>5</height><fields><field><type>ITEM</type><name>itemids</name><value><host>APC UPS Symmetra RX by SNMP</host><key>output.status[upsBasicOutputStatus]</key></value></field></fields></widget><widget><type>PLAIN_TEXT</type><y>5</y><width>8</width><height>5</height><fields><field><type>ITEM</type><name>itemids</name><value><host>APC UPS Symmetra RX by SNMP</host><key>battery.status[upsBasicBatteryStatus]</key></value></field></fields></widget><widget><type>PLAIN_TEXT</type><x>8</x><y>5</y><width>8</width><height>5</height><fields><field><type>ITEM</type><name>itemids</name><value><host>APC UPS Symmetra RX by SNMP</host><key>battery.runtime_remaining[upsAdvBatteryRunTimeRemaining]</key></value></field></fields></widget><widget><type>PLAIN_TEXT</type><x>16</x><y>5</y><width>8</width><height>5</height><fields><field><type>ITEM</type><name>itemids</name><value><host>APC UPS Symmetra RX by SNMP</host><key>battery.last_replace_date[upsBasicBatteryLastReplaceDate]</key></value></field></fields></widget><widget><type>GRAPH_CLASSIC</type><y>10</y><width>8</width><height>5</height><fields><field><type>INTEGER</type><name>source_type</name><value>0</value></field><field><type>GRAPH</type><name>graphid</name><value><host>APC UPS Symmetra RX by SNMP</host><name>Capacity of the UPS batteries</name></value></field></fields></widget><widget><type>GRAPH_CLASSIC</type><x>8</x><y>10</y><width>8</width><height>5</height><fields><field><type>INTEGER</type><name>source_type</name><value>0</value></field><field><type>GRAPH</type><name>graphid</name><value><host>APC UPS Symmetra RX by SNMP</host><name>Voltage</name></value></field></fields></widget><widget><type>GRAPH_CLASSIC</type><x>16</x><y>10</y><width>8</width><height>5</height><fields><field><type>INTEGER</type><name>source_type</name><value>0</value></field><field><type>GRAPH</type><name>graphid</name><value><host>APC UPS Symmetra RX by SNMP</host><name>Output</name></value></field></fields></widget></widgets></page></pages></dashboard></dashboards><valuemaps><valuemap><uuid>e2877a188bd24918992f8c7878550924</uuid><name>PowerNet-MIB::uioSensorStatusAlarmStatus</name><mappings><mapping><value>1</value><newvalue>Normal</newvalue></mapping><mapping><value>2</value><newvalue>Warning</newvalue></mapping><mapping><value>3</value><newvalue>Critical</newvalue></mapping><mapping><value>4</value><newvalue>Not applicable</newvalue></mapping></mappings></valuemap><valuemap><uuid>33d83523ceee4f3e916c885ebb33e8b9</uuid><name>PowerNet-MIB::upsAdvBatteryReplaceIndicator</name><mappings><mapping><value>1</value><newvalue>no Battery Needs Replacing</newvalue></mapping><mapping><value>2</value><newvalue>battery Needs Replacing</newvalue></mapping></mappings></valuemap><valuemap><uuid>c50ef9a9476d47e6935a6026bbb24d06</uuid><name>PowerNet-MIB::upsAdvInputLineFailCause</name><mappings><mapping><value>1</value><newvalue>no Transfer</newvalue></mapping><mapping><value>2</value><newvalue>High Line Voltage</newvalue></mapping><mapping><value>3</value><newvalue>Brownout</newvalue></mapping><mapping><value>4</value><newvalue>Blackout</newvalue></mapping><mapping><value>5</value><newvalue>Small Momentary Sag</newvalue></mapping><mapping><value>6</value><newvalue>Deep Momentary Sag</newvalue></mapping><mapping><value>7</value><newvalue>Small Momentary Spike</newvalue></mapping><mapping><value>8</value><newvalue>Large Momentary Spike</newvalue></mapping><mapping><value>9</value><newvalue>Self Test</newvalue></mapping><mapping><value>10</value><newvalue>Rate of Voltage Change</newvalue></mapping></mappings></valuemap><valuemap><uuid>96a985d8351f48be86c5b00472b48feb</uuid><name>PowerNet-MIB::upsBasicBatteryStatus</name><mappings><mapping><value>1</value><newvalue>Unknown</newvalue></mapping><mapping><value>2</value><newvalue>Normal</newvalue></mapping><mapping><value>3</value><newvalue>Low</newvalue></mapping><mapping><value>4</value><newvalue>In Fault Condition</newvalue></mapping></mappings></valuemap><valuemap><uuid>160f7a39770d492c93403097650c1568</uuid><name>PowerNet-MIB::upsBasicOutputStatus</name><mappings><mapping><value>1</value><newvalue>Unknown</newvalue></mapping><mapping><value>2</value><newvalue>Online</newvalue></mapping><mapping><value>3</value><newvalue>On Battery</newvalue></mapping><mapping><value>4</value><newvalue>On Smart Boost</newvalue></mapping><mapping><value>5</value><newvalue>Timed Sleeping</newvalue></mapping><mapping><value>6</value><newvalue>Software Bypass</newvalue></mapping><mapping><value>7</value><newvalue>Off</newvalue></mapping><mapping><value>8</value><newvalue>Rebooting</newvalue></mapping><mapping><value>9</value><newvalue>Switched Bypass</newvalue></mapping><mapping><value>10</value><newvalue>Hardware Failure Bypass</newvalue></mapping><mapping><value>11</value><newvalue>Sleeping Until Power Return</newvalue></mapping><mapping><value>12</value><newvalue>On Smart Trim</newvalue></mapping><mapping><value>13</value><newvalue>Eco Mode</newvalue></mapping><mapping><value>14</value><newvalue>Hot Standby</newvalue></mapping><mapping><value>15</value><newvalue>On Battery Test</newvalue></mapping><mapping><value>16</value><newvalue>Emergency Static Bypass</newvalue></mapping><mapping><value>17</value><newvalue>Static Bypass Standby</newvalue></mapping><mapping><value>18</value><newvalue>Power Saving Mode</newvalue></mapping><mapping><value>19</value><newvalue>Spot Mode</newvalue></mapping><mapping><value>20</value><newvalue>E-Conversion</newvalue></mapping><mapping><value>21</value><newvalue>Charger Spotmode</newvalue></mapping><mapping><value>22</value><newvalue>Inverter Spotmode</newvalue></mapping><mapping><value>23</value><newvalue>Active Load</newvalue></mapping><mapping><value>24</value><newvalue>Battery Discharge Spotmode</newvalue></mapping><mapping><value>25</value><newvalue>Inverter Standby</newvalue></mapping><mapping><value>26</value><newvalue>Charger Only</newvalue></mapping></mappings></valuemap><valuemap><uuid>cc7a368057bc47eeb834dc9363183c59</uuid><name>zabbix.host.available</name><mappings><mapping><value>0</value><newvalue>not available</newvalue></mapping><mapping><value>1</value><newvalue>available</newvalue></mapping><mapping><value>2</value><newvalue>unknown</newvalue></mapping></mappings></valuemap></valuemaps></template></templates><triggers><trigger><uuid>990c0545543c42a78022589838a8a1ff</uuid><expression>(last(/APC UPS Symmetra RX by SNMP/system.hw.uptime[hrSystemUptime.0])&gt;0 and last(/APC UPS Symmetra RX by SNMP/system.hw.uptime[hrSystemUptime.0])&lt;10m) or (last(/APC UPS Symmetra RX by SNMP/system.hw.uptime[hrSystemUptime.0])=0 and last(/APC UPS Symmetra RX by SNMP/system.net.uptime[sysUpTime.0])&lt;10m)</expression><name>Host has been restarted</name><event_name>{HOST.NAME} has been restarted (uptime &lt; 10m)</event_name><priority>WARNING</priority><description>Uptime is less than 10 minutes.</description><manual_close>YES</manual_close><dependencies><dependency><name>No SNMP data collection</name><expression>max(/APC UPS Symmetra RX by SNMP/zabbix[host,snmp,available],{$SNMP.TIMEOUT})=0</expression></dependency></dependencies><tags><tag><tag>scope</tag><value>notice</value></tag></tags></trigger></triggers><graphs><graph><uuid>69ef37f00b0249bb98f381b483280dd1</uuid><name>Capacity of the UPS batteries</name><type>PIE</type><graph_items><graph_item><color>1A7C11</color><item><host>APC UPS Symmetra RX by SNMP</host><key>battery.capacity[upsHighPrecBatteryCapacity]</key></item></graph_item></graph_items></graph><graph><uuid>782c8a349b7f4f93a65aeaa058454b14</uuid><name>Output</name><graph_items><graph_item><color>1A7C11</color><item><host>APC UPS Symmetra RX by SNMP</host><key>output.current[upsHighPrecOutputCurrent]</key></item></graph_item><graph_item><sortorder>1</sortorder><color>2774A4</color><item><host>APC UPS Symmetra RX by SNMP</host><key>output.load[upsHighPrecOutputLoad]</key></item></graph_item></graph_items></graph><graph><uuid>8bc9d8e4bb284134b67498daccb85d5e</uuid><name>Voltage</name><graph_items><graph_item><color>1A7C11</color><item><host>APC UPS Symmetra RX by SNMP</host><key>input.voltage[upsHighPrecInputLineVoltage]</key></item></graph_item><graph_item><sortorder>1</sortorder><color>2774A4</color><item><host>APC UPS Symmetra RX by SNMP</host><key>output.voltage[upsHighPrecOutputVoltage]</key></item></graph_item></graph_items></graph></graphs></zabbix_export>
